{"cameraMode":{"drawMode":0,"name":"Shaded","section":"Shading Mode"},"sceneLighting":true,"audioPlay":false,"sceneViewState":{"showFog":true,"showMaterialUpdate":false,"showSkybox":true,"showFlares":true,"showImageEffects":true,"showParticleSystems":true},"in2DMode":false,"pivot":{"x":-3.2823920249938967,"y":-1.3197822570800782,"z":-3.1920981407165529},"rotation":{"x":-0.14045336842536927,"y":0.7549813985824585,"z":-0.17185117304325105,"w":-0.6170440912246704},"size":5.14805793762207,"orthographic":false}